MANIFEST.in
README.rst
requirements.txt
setup.py
version.py
JohnnieRunner.egg-info/PKG-INFO
JohnnieRunner.egg-info/SOURCES.txt
JohnnieRunner.egg-info/dependency_links.txt
JohnnieRunner.egg-info/requires.txt
JohnnieRunner.egg-info/top_level.txt
johnnie/__init__.py
johnnie/engine.py
johnnie/exception.py
johnnie/model.py
johnnie/types.py