Metadata-Version: 1.1
Name: JohnnieRunner
Version: 0.0.1
Summary: JohnnieRunner is SQLAlchemy Wrapper for Active Record pattern O/R Mapper
Home-page: https://github.com/teitei-tk/JohnnieRunner
Author: teitei-tk
Author-email: teitei.tk@gmail.com
License: MIT
Download-URL: https://github.com/teitei-tk/JohnnieRunner/archive/master.tar.gz
Keywords: orm,ormapper,o/r mapper,ActiveRecord,SQLAlchemy
Platform: UNKNOWN
Classifier: Development Status :: 3 - Alpha
Classifier: License :: OSI Approved :: MIT License
Classifier: Programming Language :: Python
Classifier: Programming Language :: Python :: 2.6
Classifier: Programming Language :: Python :: 2.7
Classifier: Programming Language :: Python :: 3
Classifier: Topic :: Software Development
Classifier: Topic :: Database
Classifier: Topic :: Database :: Front-Ends
Classifier: Topic :: Software Development :: Libraries
